README.rst
setup.cfg
setup.py
sqlitent.py
sqlitent.egg-info/PKG-INFO
sqlitent.egg-info/SOURCES.txt
sqlitent.egg-info/dependency_links.txt
sqlitent.egg-info/top_level.txt