Metadata-Version: 1.1
Name: sqlitent
Version: 0.2.1
Summary: namedtuples inside set-like sqlite databases
Home-page: https://github.com/digitalmensch/sqlitent
Author: Tobias Ammann
Author-email: UNKNOWN
License: MIT
Download-URL: https://pypi.python.org/pypi/sqlitent
Keywords: sqlite,persistent set,namedtuple
Platform: any
Classifier: Development Status :: 4 - Beta
Classifier: Intended Audience :: Developers
Classifier: License :: OSI Approved :: MIT License
Classifier: Operating System :: OS Independent
Classifier: Programming Language :: Python
Classifier: Programming Language :: Python :: 3.6
Classifier: Topic :: Database :: Front-Ends
